{
  "firstLayout": "",
  "gdVersion": {
    "build": 239,
    "major": 5,
    "minor": 5,
    "revision": 0
  },
  "properties": {
    "adaptGameResolutionAtRuntime": false,
    "antialiasingMode": "MSAA",
    "antialisingEnabledOnMobile": false,
    "folderProject": true,
    "orientation": "landscape",
    "packageName": "com.example.gamename",
    "pixelsRounding": true,
    "projectUuid": "104e5d04-e3ab-455f-bec4-99d9a6a12416",
    "scaleMode": "nearest",
    "sceneResourcesPreloading": "never",
    "sceneResourcesUnloading": "at-scene-exit",
    "sizeOnStartupMode": "",
    "templateSlug": "",
    "version": "0.0.0",
    "name": "Adrift",
    "description": "",
    "author": "P4rgeDev",
    "windowWidth": 1280,
    "windowHeight": 720,
    "latestCompilationDirectory": "",
    "maxFPS": 240,
    "minFPS": 60,
    "verticalSync": false,
    "platformSpecificAssets": {
      "android-icon-144": "",
      "android-icon-192": "",
      "android-icon-36": "",
      "android-icon-48": "",
      "android-icon-72": "",
      "android-icon-96": "",
      "android-windowSplashScreenAnimatedIcon": "",
      "desktop-icon-512": "",
      "ios-icon-100": "",
      "ios-icon-1024": "",
      "ios-icon-114": "",
      "ios-icon-120": "",
      "ios-icon-144": "",
      "ios-icon-152": "",
      "ios-icon-167": "",
      "ios-icon-180": "",
      "ios-icon-20": "",
      "ios-icon-29": "",
      "ios-icon-40": "",
      "ios-icon-50": "",
      "ios-icon-57": "",
      "ios-icon-58": "",
      "ios-icon-60": "",
      "ios-icon-72": "",
      "ios-icon-76": "",
      "ios-icon-80": "",
      "ios-icon-87": ""
    },
    "loadingScreen": {
      "backgroundColor": 0,
      "backgroundFadeInDuration": 0.2,
      "backgroundImageResourceName": "",
      "gdevelopLogoStyle": "light",
      "logoAndProgressFadeInDuration": 0.2,
      "logoAndProgressLogoFadeInDelay": 0,
      "minDuration": 1.5,
      "progressBarColor": 16777215,
      "progressBarHeight": 20,
      "progressBarMaxWidth": 200,
      "progressBarMinWidth": 40,
      "progressBarWidthPercent": 30,
      "showGDevelopSplash": false,
      "showProgressBar": true
    },
    "watermark": {
      "placement": "bottom-left",
      "showWatermark": false
    },
    "authorIds": [],
    "authorUsernames": [],
    "categories": [],
    "playableDevices": [],
    "extensionProperties": [
      {
        "extension": "Steamworks",
        "property": "AppID",
        "value": "480"
      },
      {
        "extension": "Steamworks",
        "property": "RequireSteam",
        "value": "true"
      }
    ],
    "platforms": [
      {
        "name": "GDevelop JS platform"
      }
    ],
    "currentPlatform": "GDevelop JS platform"
  },
  "resources": {
    "resources": [
      {
        "file": "assets/player.png",
        "kind": "image",
        "metadata": "{\"extension\":\".png\"}",
        "name": "player",
        "smoothed": false,
        "userAdded": false
      }
    ],
    "resourceFolders": []
  },
  "objects": [
    {
      "assetStoreId": "",
      "name": "SettingsHolder",
      "type": "TileMap::SimpleTileMap",
      "variables": [
        {
          "name": "Left",
          "type": "string",
          "value": "0"
        },
        {
          "name": "Right",
          "type": "string",
          "value": "0"
        },
        {
          "name": "Up",
          "type": "string",
          "value": "0"
        },
        {
          "name": "Down",
          "type": "string",
          "value": "0"
        },
        {
          "name": "Dash",
          "type": "string",
          "value": "0"
        },
        {
          "name": "OpenDoors",
          "type": "string",
          "value": "0"
        },
        {
          "name": "FullscreenToggle",
          "type": "string",
          "value": "0"
        },
        {
          "name": "debugmenu_hidden",
          "type": "string",
          "value": "0"
        },
        {
          "name": "Autosave",
          "type": "boolean",
          "value": true
        },
        {
          "name": "AutosaveTimer",
          "type": "number",
          "value": 0
        },
        {
          "name": "ManualSave",
          "type": "string",
          "value": "0"
        },
        {
          "name": "SaveLocation",
          "type": "string",
          "value": "0"
        }
      ],
      "effects": [],
      "behaviors": [],
      "content": {
        "atlasImage": "",
        "rowCount": 1,
        "columnCount": 1,
        "tileSize": 1,
        "tilesWithHitBox": ""
      }
    }
  ],
  "objectsFolderStructure": {
    "folderName": "__ROOT",
    "children": [
      {
        "objectName": "SettingsHolder"
      }
    ]
  },
  "objectsGroups": [],
  "variables": [],
  "layouts": [
    {
      "__REFERENCE_TO_SPLIT_OBJECT": true,
      "referenceTo": "/layouts/untitled-scene"
    },
    {
      "__REFERENCE_TO_SPLIT_OBJECT": true,
      "referenceTo": "/layouts/settings"
    }
  ],
  "externalEvents": [],
  "eventsFunctionsExtensions": [],
  "externalLayouts": []
}